{
  "aerialway": {
    "height": 38,
    "pixelRatio": 2,
    "width": 38,
    "x": 0,
    "y": 0
  },
  "airfield": {
    "height": 38,
    "pixelRatio": 2,
    "width": 38,
    "x": 38,
    "y": 0
  },
  "airport": {
    "height": 38,
    "pixelRatio": 2,
    "width": 38,
    "x": 0,
    "y": 38
  },
  "alcohol-shop": {
    "height": 38,
    "pixelRatio": 2,
    "width": 38,
    "x": 38,
    "y": 38
  },
  "american-football": {
    "height": 38,
    "pixelRatio": 2,
    "width": 38,
    "x": 76,
    "y": 0
  },
  "amusement-park": {
    "height": 38,
    "pixelRatio": 2,
    "width": 38,
    "x": 114,
    "y": 0
  },
  "aquarium": {
    "height": 38,
    "pixelRatio": 2,
    "width": 38,
    "x": 76,
    "y": 38
  },
  "arrow": {
    "height": 38,
    "pixelRatio": 2,
    "width": 38,
    "x": 114,
    "y": 38
  },
  "art-gallery": {
    "height": 38,
    "pixelRatio": 2,
    "width": 38,
    "x": 0,
    "y": 76
  },
  "attraction": {
    "height": 38,
    "pixelRatio": 2,
    "width": 38,
    "x": 38,
    "y": 76
  },
  "bakery": {
    "height": 38,
    "pixelRatio": 2,
    "width": 38,
    "x": 76,
    "y": 76
  },
  "bank": {
    "height": 38,
    "pixelRatio": 2,
    "width": 38,
    "x": 114,
    "y": 76
  },
  "bank-JP": {
    "height": 38,
    "pixelRatio": 2,
    "width": 38,
    "x": 0,
    "y": 114
  },
  "bar": {
    "height": 38,
    "pixelRatio": 2,
    "width": 38,
    "x": 38,
    "y": 114
  },
  "barrier": {
    "height": 38,
    "pixelRatio": 2,
    "width": 38,
    "x": 76,
    "y": 114
  },
  "baseball": {
    "height": 38,
    "pixelRatio": 2,
    "width": 38,
    "x": 114,
    "y": 114
  },
  "basketball": {
    "height": 38,
    "pixelRatio": 2,
    "width": 38,
    "x": 152,
    "y": 0
  },
  "bbq": {
    "height": 38,
    "pixelRatio": 2,
    "width": 38,
    "x": 190,
    "y": 0
  },
  "beach": {
    "height": 38,
    "pixelRatio": 2,
    "width": 38,
    "x": 228,
    "y": 0
  },
  "beer": {
    "height": 38,
    "pixelRatio": 2,
    "width": 38,
    "x": 266,
    "y": 0
  },
  "bicycle": {
    "height": 38,
    "pixelRatio": 2,
    "width": 38,
    "x": 152,
    "y": 38
  },
  "bicycle-share": {
    "height": 38,
    "pixelRatio": 2,
    "width": 38,
    "x": 190,
    "y": 38
  },
  "blood-bank": {
    "height": 38,
    "pixelRatio": 2,
    "width": 38,
    "x": 228,
    "y": 38
  },
  "bowling-alley": {
    "height": 38,
    "pixelRatio": 2,
    "width": 38,
    "x": 266,
    "y": 38
  },
  "bridge": {
    "height": 38,
    "pixelRatio": 2,
    "width": 38,
    "x": 152,
    "y": 76
  },
  "building": {
    "height": 38,
    "pixelRatio": 2,
    "width": 38,
    "x": 190,
    "y": 76
  },
  "building-alt1": {
    "height": 38,
    "pixelRatio": 2,
    "width": 38,
    "x": 228,
    "y": 76
  },
  "bus": {
    "height": 38,
    "pixelRatio": 2,
    "width": 38,
    "x": 266,
    "y": 76
  },
  "cafe": {
    "height": 38,
    "pixelRatio": 2,
    "width": 38,
    "x": 152,
    "y": 114
  },
  "campsite": {
    "height": 38,
    "pixelRatio": 2,
    "width": 38,
    "x": 190,
    "y": 114
  },
  "car": {
    "height": 38,
    "pixelRatio": 2,
    "width": 38,
    "x": 228,
    "y": 114
  },
  "car-rental": {
    "height": 38,
    "pixelRatio": 2,
    "width": 38,
    "x": 266,
    "y": 114
  },
  "car-repair": {
    "height": 38,
    "pixelRatio": 2,
    "width": 38,
    "x": 0,
    "y": 152
  },
  "casino": {
    "height": 38,
    "pixelRatio": 2,
    "width": 38,
    "x": 38,
    "y": 152
  },
  "castle": {
    "height": 38,
    "pixelRatio": 2,
    "width": 38,
    "x": 76,
    "y": 152
  },
  "castle-JP": {
    "height": 38,
    "pixelRatio": 2,
    "width": 38,
    "x": 114,
    "y": 152
  },
  "caution": {
    "height": 38,
    "pixelRatio": 2,
    "width": 38,
    "x": 152,
    "y": 152
  },
  "cemetery": {
    "height": 38,
    "pixelRatio": 2,
    "width": 38,
    "x": 190,
    "y": 152
  },
  "cemetery-JP": {
    "height": 38,
    "pixelRatio": 2,
    "width": 38,
    "x": 228,
    "y": 152
  },
  "charging-station": {
    "height": 38,
    "pixelRatio": 2,
    "width": 38,
    "x": 266,
    "y": 152
  },
  "cinema": {
    "height": 38,
    "pixelRatio": 2,
    "width": 38,
    "x": 0,
    "y": 190
  },
  "circle": {
    "height": 38,
    "pixelRatio": 2,
    "width": 38,
    "x": 38,
    "y": 190
  },
  "circle-stroked": {
    "height": 38,
    "pixelRatio": 2,
    "width": 38,
    "x": 76,
    "y": 190
  },
  "city": {
    "height": 38,
    "pixelRatio": 2,
    "width": 38,
    "x": 114,
    "y": 190
  },
  "clothing-store": {
    "height": 38,
    "pixelRatio": 2,
    "width": 38,
    "x": 152,
    "y": 190
  },
  "college": {
    "height": 38,
    "pixelRatio": 2,
    "width": 38,
    "x": 190,
    "y": 190
  },
  "college-JP": {
    "height": 38,
    "pixelRatio": 2,
    "width": 38,
    "x": 228,
    "y": 190
  },
  "commercial": {
    "height": 38,
    "pixelRatio": 2,
    "width": 38,
    "x": 266,
    "y": 190
  },
  "communications-tower": {
    "height": 38,
    "pixelRatio": 2,
    "width": 38,
    "x": 0,
    "y": 228
  },
  "confectionery": {
    "height": 38,
    "pixelRatio": 2,
    "width": 38,
    "x": 38,
    "y": 228
  },
  "construction": {
    "height": 38,
    "pixelRatio": 2,
    "width": 38,
    "x": 76,
    "y": 228
  },
  "convenience": {
    "height": 38,
    "pixelRatio": 2,
    "width": 38,
    "x": 114,
    "y": 228
  },
  "cricket": {
    "height": 38,
    "pixelRatio": 2,
    "width": 38,
    "x": 152,
    "y": 228
  },
  "cross": {
    "height": 38,
    "pixelRatio": 2,
    "width": 38,
    "x": 190,
    "y": 228
  },
  "dam": {
    "height": 38,
    "pixelRatio": 2,
    "width": 38,
    "x": 228,
    "y": 228
  },
  "danger": {
    "height": 38,
    "pixelRatio": 2,
    "width": 38,
    "x": 266,
    "y": 228
  },
  "defibrillator": {
    "height": 38,
    "pixelRatio": 2,
    "width": 38,
    "x": 0,
    "y": 266
  },
  "dentist": {
    "height": 38,
    "pixelRatio": 2,
    "width": 38,
    "x": 38,
    "y": 266
  },
  "diamond": {
    "height": 38,
    "pixelRatio": 2,
    "width": 38,
    "x": 76,
    "y": 266
  },
  "doctor": {
    "height": 38,
    "pixelRatio": 2,
    "width": 38,
    "x": 114,
    "y": 266
  },
  "dog-park": {
    "height": 38,
    "pixelRatio": 2,
    "width": 38,
    "x": 152,
    "y": 266
  },
  "drinking-water": {
    "height": 38,
    "pixelRatio": 2,
    "width": 38,
    "x": 190,
    "y": 266
  },
  "elevator": {
    "height": 38,
    "pixelRatio": 2,
    "width": 38,
    "x": 228,
    "y": 266
  },
  "embassy": {
    "height": 38,
    "pixelRatio": 2,
    "width": 38,
    "x": 266,
    "y": 266
  },
  "emergency-phone": {
    "height": 38,
    "pixelRatio": 2,
    "width": 38,
    "x": 304,
    "y": 0
  },
  "entrance": {
    "height": 38,
    "pixelRatio": 2,
    "width": 38,
    "x": 342,
    "y": 0
  },
  "entrance-alt1": {
    "height": 38,
    "pixelRatio": 2,
    "width": 38,
    "x": 380,
    "y": 0
  },
  "farm": {
    "height": 38,
    "pixelRatio": 2,
    "width": 38,
    "x": 418,
    "y": 0
  },
  "fast-food": {
    "height": 38,
    "pixelRatio": 2,
    "width": 38,
    "x": 456,
    "y": 0
  },
  "fence": {
    "height": 38,
    "pixelRatio": 2,
    "width": 38,
    "x": 494,
    "y": 0
  },
  "ferry": {
    "height": 38,
    "pixelRatio": 2,
    "width": 38,
    "x": 532,
    "y": 0
  },
  "ferry-JP": {
    "height": 38,
    "pixelRatio": 2,
    "width": 38,
    "x": 570,
    "y": 0
  },
  "fire-station": {
    "height": 38,
    "pixelRatio": 2,
    "width": 38,
    "x": 304,
    "y": 38
  },
  "fire-station-JP": {
    "height": 38,
    "pixelRatio": 2,
    "width": 38,
    "x": 342,
    "y": 38
  },
  "fitness-centre": {
    "height": 38,
    "pixelRatio": 2,
    "width": 38,
    "x": 380,
    "y": 38
  },
  "florist": {
    "height": 38,
    "pixelRatio": 2,
    "width": 38,
    "x": 418,
    "y": 38
  },
  "fuel": {
    "height": 38,
    "pixelRatio": 2,
    "width": 38,
    "x": 456,
    "y": 38
  },
  "furniture": {
    "height": 38,
    "pixelRatio": 2,
    "width": 38,
    "x": 494,
    "y": 38
  },
  "gaming": {
    "height": 38,
    "pixelRatio": 2,
    "width": 38,
    "x": 532,
    "y": 38
  },
  "garden": {
    "height": 38,
    "pixelRatio": 2,
    "width": 38,
    "x": 570,
    "y": 38
  },
  "garden-centre": {
    "height": 38,
    "pixelRatio": 2,
    "width": 38,
    "x": 304,
    "y": 76
  },
  "gift": {
    "height": 38,
    "pixelRatio": 2,
    "width": 38,
    "x": 342,
    "y": 76
  },
  "globe": {
    "height": 38,
    "pixelRatio": 2,
    "width": 38,
    "x": 380,
    "y": 76
  },
  "golf": {
    "height": 38,
    "pixelRatio": 2,
    "width": 38,
    "x": 418,
    "y": 76
  },
  "grocery": {
    "height": 38,
    "pixelRatio": 2,
    "width": 38,
    "x": 456,
    "y": 76
  },
  "hairdresser": {
    "height": 38,
    "pixelRatio": 2,
    "width": 38,
    "x": 494,
    "y": 76
  },
  "harbor": {
    "height": 38,
    "pixelRatio": 2,
    "width": 38,
    "x": 532,
    "y": 76
  },
  "hardware": {
    "height": 38,
    "pixelRatio": 2,
    "width": 38,
    "x": 570,
    "y": 76
  },
  "heart": {
    "height": 38,
    "pixelRatio": 2,
    "width": 38,
    "x": 304,
    "y": 114
  },
  "heliport": {
    "height": 38,
    "pixelRatio": 2,
    "width": 38,
    "x": 342,
    "y": 114
  },
  "highway-rest-area": {
    "height": 38,
    "pixelRatio": 2,
    "width": 38,
    "x": 380,
    "y": 114
  },
  "home": {
    "height": 38,
    "pixelRatio": 2,
    "width": 38,
    "x": 418,
    "y": 114
  },
  "horse-riding": {
    "height": 38,
    "pixelRatio": 2,
    "width": 38,
    "x": 456,
    "y": 114
  },
  "hospital": {
    "height": 38,
    "pixelRatio": 2,
    "width": 38,
    "x": 494,
    "y": 114
  },
  "hospital-JP": {
    "height": 38,
    "pixelRatio": 2,
    "width": 38,
    "x": 532,
    "y": 114
  },
  "hot-spring": {
    "height": 38,
    "pixelRatio": 2,
    "width": 38,
    "x": 570,
    "y": 114
  },
  "ice-cream": {
    "height": 38,
    "pixelRatio": 2,
    "width": 38,
    "x": 304,
    "y": 152
  },
  "industry": {
    "height": 38,
    "pixelRatio": 2,
    "width": 38,
    "x": 342,
    "y": 152
  },
  "information": {
    "height": 38,
    "pixelRatio": 2,
    "width": 38,
    "x": 380,
    "y": 152
  },
  "jewelry-store": {
    "height": 38,
    "pixelRatio": 2,
    "width": 38,
    "x": 418,
    "y": 152
  },
  "karaoke": {
    "height": 38,
    "pixelRatio": 2,
    "width": 38,
    "x": 456,
    "y": 152
  },
  "landmark": {
    "height": 38,
    "pixelRatio": 2,
    "width": 38,
    "x": 494,
    "y": 152
  },
  "landmark-JP": {
    "height": 38,
    "pixelRatio": 2,
    "width": 38,
    "x": 532,
    "y": 152
  },
  "landuse": {
    "height": 38,
    "pixelRatio": 2,
    "width": 38,
    "x": 570,
    "y": 152
  },
  "laundry": {
    "height": 38,
    "pixelRatio": 2,
    "width": 38,
    "x": 304,
    "y": 190
  },
  "library": {
    "height": 38,
    "pixelRatio": 2,
    "width": 38,
    "x": 342,
    "y": 190
  },
  "lighthouse": {
    "height": 38,
    "pixelRatio": 2,
    "width": 38,
    "x": 380,
    "y": 190
  },
  "lighthouse-JP": {
    "height": 38,
    "pixelRatio": 2,
    "width": 38,
    "x": 418,
    "y": 190
  },
  "lodging": {
    "height": 38,
    "pixelRatio": 2,
    "width": 38,
    "x": 456,
    "y": 190
  },
  "logging": {
    "height": 38,
    "pixelRatio": 2,
    "width": 38,
    "x": 494,
    "y": 190
  },
  "marker": {
    "height": 38,
    "pixelRatio": 2,
    "width": 38,
    "x": 532,
    "y": 190
  },
  "marker-stroked": {
    "height": 38,
    "pixelRatio": 2,
    "width": 38,
    "x": 570,
    "y": 190
  },
  "mobile-phone": {
    "height": 38,
    "pixelRatio": 2,
    "width": 38,
    "x": 304,
    "y": 228
  },
  "monument": {
    "height": 38,
    "pixelRatio": 2,
    "width": 38,
    "x": 342,
    "y": 228
  },
  "monument-JP": {
    "height": 38,
    "pixelRatio": 2,
    "width": 38,
    "x": 380,
    "y": 228
  },
  "mountain": {
    "height": 38,
    "pixelRatio": 2,
    "width": 38,
    "x": 418,
    "y": 228
  },
  "museum": {
    "height": 38,
    "pixelRatio": 2,
    "width": 38,
    "x": 456,
    "y": 228
  },
  "music": {
    "height": 38,
    "pixelRatio": 2,
    "width": 38,
    "x": 494,
    "y": 228
  },
  "natural": {
    "height": 38,
    "pixelRatio": 2,
    "width": 38,
    "x": 532,
    "y": 228
  },
  "observation-tower": {
    "height": 38,
    "pixelRatio": 2,
    "width": 38,
    "x": 570,
    "y": 228
  },
  "optician": {
    "height": 38,
    "pixelRatio": 2,
    "width": 38,
    "x": 304,
    "y": 266
  },
  "paint": {
    "height": 38,
    "pixelRatio": 2,
    "width": 38,
    "x": 342,
    "y": 266
  },
  "park": {
    "height": 38,
    "pixelRatio": 2,
    "width": 38,
    "x": 380,
    "y": 266
  },
  "park-alt1": {
    "height": 38,
    "pixelRatio": 2,
    "width": 38,
    "x": 418,
    "y": 266
  },
  "parking": {
    "height": 38,
    "pixelRatio": 2,
    "width": 38,
    "x": 456,
    "y": 266
  },
  "parking-garage": {
    "height": 38,
    "pixelRatio": 2,
    "width": 38,
    "x": 494,
    "y": 266
  },
  "pharmacy": {
    "height": 38,
    "pixelRatio": 2,
    "width": 38,
    "x": 532,
    "y": 266
  },
  "picnic-site": {
    "height": 38,
    "pixelRatio": 2,
    "width": 38,
    "x": 570,
    "y": 266
  },
  "pitch": {
    "height": 38,
    "pixelRatio": 2,
    "width": 38,
    "x": 0,
    "y": 304
  },
  "place-of-worship": {
    "height": 38,
    "pixelRatio": 2,
    "width": 38,
    "x": 38,
    "y": 304
  },
  "playground": {
    "height": 38,
    "pixelRatio": 2,
    "width": 38,
    "x": 76,
    "y": 304
  },
  "police": {
    "height": 38,
    "pixelRatio": 2,
    "width": 38,
    "x": 114,
    "y": 304
  },
  "police-JP": {
    "height": 38,
    "pixelRatio": 2,
    "width": 38,
    "x": 152,
    "y": 304
  },
  "post": {
    "height": 38,
    "pixelRatio": 2,
    "width": 38,
    "x": 190,
    "y": 304
  },
  "post-JP": {
    "height": 38,
    "pixelRatio": 2,
    "width": 38,
    "x": 228,
    "y": 304
  },
  "prison": {
    "height": 38,
    "pixelRatio": 2,
    "width": 38,
    "x": 266,
    "y": 304
  },
  "racetrack": {
    "height": 38,
    "pixelRatio": 2,
    "width": 38,
    "x": 304,
    "y": 304
  },
  "racetrack-boat": {
    "height": 38,
    "pixelRatio": 2,
    "width": 38,
    "x": 342,
    "y": 304
  },
  "racetrack-cycling": {
    "height": 38,
    "pixelRatio": 2,
    "width": 38,
    "x": 380,
    "y": 304
  },
  "racetrack-horse": {
    "height": 38,
    "pixelRatio": 2,
    "width": 38,
    "x": 418,
    "y": 304
  },
  "rail": {
    "height": 38,
    "pixelRatio": 2,
    "width": 38,
    "x": 456,
    "y": 304
  },
  "rail-light": {
    "height": 38,
    "pixelRatio": 2,
    "width": 38,
    "x": 494,
    "y": 304
  },
  "rail-metro": {
    "height": 38,
    "pixelRatio": 2,
    "width": 38,
    "x": 532,
    "y": 304
  },
  "ranger-station": {
    "height": 38,
    "pixelRatio": 2,
    "width": 38,
    "x": 570,
    "y": 304
  },
  "recycling": {
    "height": 38,
    "pixelRatio": 2,
    "width": 38,
    "x": 0,
    "y": 342
  },
  "religious-buddhist": {
    "height": 38,
    "pixelRatio": 2,
    "width": 38,
    "x": 38,
    "y": 342
  },
  "religious-christian": {
    "height": 38,
    "pixelRatio": 2,
    "width": 38,
    "x": 76,
    "y": 342
  },
  "religious-jewish": {
    "height": 38,
    "pixelRatio": 2,
    "width": 38,
    "x": 114,
    "y": 342
  },
  "religious-muslim": {
    "height": 38,
    "pixelRatio": 2,
    "width": 38,
    "x": 152,
    "y": 342
  },
  "religious-shinto": {
    "height": 38,
    "pixelRatio": 2,
    "width": 38,
    "x": 190,
    "y": 342
  },
  "residential-community": {
    "height": 38,
    "pixelRatio": 2,
    "width": 38,
    "x": 228,
    "y": 342
  },
  "restaurant": {
    "height": 38,
    "pixelRatio": 2,
    "width": 38,
    "x": 266,
    "y": 342
  },
  "restaurant-bbq": {
    "height": 38,
    "pixelRatio": 2,
    "width": 38,
    "x": 304,
    "y": 342
  },
  "restaurant-noodle": {
    "height": 38,
    "pixelRatio": 2,
    "width": 38,
    "x": 342,
    "y": 342
  },
  "restaurant-pizza": {
    "height": 38,
    "pixelRatio": 2,
    "width": 38,
    "x": 380,
    "y": 342
  },
  "restaurant-seafood": {
    "height": 38,
    "pixelRatio": 2,
    "width": 38,
    "x": 418,
    "y": 342
  },
  "restaurant-sushi": {
    "height": 38,
    "pixelRatio": 2,
    "width": 38,
    "x": 456,
    "y": 342
  },
  "road-accident": {
    "height": 38,
    "pixelRatio": 2,
    "width": 38,
    "x": 494,
    "y": 342
  },
  "roadblock": {
    "height": 38,
    "pixelRatio": 2,
    "width": 38,
    "x": 532,
    "y": 342
  },
  "rocket": {
    "height": 38,
    "pixelRatio": 2,
    "width": 38,
    "x": 570,
    "y": 342
  },
  "school": {
    "height": 38,
    "pixelRatio": 2,
    "width": 38,
    "x": 0,
    "y": 380
  },
  "school-JP": {
    "height": 38,
    "pixelRatio": 2,
    "width": 38,
    "x": 38,
    "y": 380
  },
  "scooter": {
    "height": 38,
    "pixelRatio": 2,
    "width": 38,
    "x": 76,
    "y": 380
  },
  "shelter": {
    "height": 38,
    "pixelRatio": 2,
    "width": 38,
    "x": 114,
    "y": 380
  },
  "shoe": {
    "height": 38,
    "pixelRatio": 2,
    "width": 38,
    "x": 152,
    "y": 380
  },
  "shop": {
    "height": 38,
    "pixelRatio": 2,
    "width": 38,
    "x": 190,
    "y": 380
  },
  "skateboard": {
    "height": 38,
    "pixelRatio": 2,
    "width": 38,
    "x": 228,
    "y": 380
  },
  "skiing": {
    "height": 38,
    "pixelRatio": 2,
    "width": 38,
    "x": 266,
    "y": 380
  },
  "slaughterhouse": {
    "height": 38,
    "pixelRatio": 2,
    "width": 38,
    "x": 304,
    "y": 380
  },
  "slipway": {
    "height": 38,
    "pixelRatio": 2,
    "width": 38,
    "x": 342,
    "y": 380
  },
  "snowmobile": {
    "height": 38,
    "pixelRatio": 2,
    "width": 38,
    "x": 380,
    "y": 380
  },
  "soccer": {
    "height": 38,
    "pixelRatio": 2,
    "width": 38,
    "x": 418,
    "y": 380
  },
  "square": {
    "height": 38,
    "pixelRatio": 2,
    "width": 38,
    "x": 456,
    "y": 380
  },
  "square-stroked": {
    "height": 38,
    "pixelRatio": 2,
    "width": 38,
    "x": 494,
    "y": 380
  },
  "stadium": {
    "height": 38,
    "pixelRatio": 2,
    "width": 38,
    "x": 532,
    "y": 380
  },
  "star": {
    "height": 38,
    "pixelRatio": 2,
    "width": 38,
    "x": 570,
    "y": 380
  },
  "star-stroked": {
    "height": 38,
    "pixelRatio": 2,
    "width": 38,
    "x": 0,
    "y": 418
  },
  "suitcase": {
    "height": 38,
    "pixelRatio": 2,
    "width": 38,
    "x": 38,
    "y": 418
  },
  "swimming": {
    "height": 38,
    "pixelRatio": 2,
    "width": 38,
    "x": 76,
    "y": 418
  },
  "table-tennis": {
    "height": 38,
    "pixelRatio": 2,
    "width": 38,
    "x": 114,
    "y": 418
  },
  "teahouse": {
    "height": 38,
    "pixelRatio": 2,
    "width": 38,
    "x": 152,
    "y": 418
  },
  "telephone": {
    "height": 38,
    "pixelRatio": 2,
    "width": 38,
    "x": 190,
    "y": 418
  },
  "tennis": {
    "height": 38,
    "pixelRatio": 2,
    "width": 38,
    "x": 228,
    "y": 418
  },
  "theatre": {
    "height": 38,
    "pixelRatio": 2,
    "width": 38,
    "x": 266,
    "y": 418
  },
  "toilet": {
    "height": 38,
    "pixelRatio": 2,
    "width": 38,
    "x": 304,
    "y": 418
  },
  "town": {
    "height": 38,
    "pixelRatio": 2,
    "width": 38,
    "x": 342,
    "y": 418
  },
  "town-hall": {
    "height": 38,
    "pixelRatio": 2,
    "width": 38,
    "x": 380,
    "y": 418
  },
  "triangle": {
    "height": 38,
    "pixelRatio": 2,
    "width": 38,
    "x": 418,
    "y": 418
  },
  "triangle-stroked": {
    "height": 38,
    "pixelRatio": 2,
    "width": 38,
    "x": 456,
    "y": 418
  },
  "veterinary": {
    "height": 38,
    "pixelRatio": 2,
    "width": 38,
    "x": 494,
    "y": 418
  },
  "viewpoint": {
    "height": 38,
    "pixelRatio": 2,
    "width": 38,
    "x": 532,
    "y": 418
  },
  "village": {
    "height": 38,
    "pixelRatio": 2,
    "width": 38,
    "x": 570,
    "y": 418
  },
  "volcano": {
    "height": 38,
    "pixelRatio": 2,
    "width": 38,
    "x": 0,
    "y": 456
  },
  "volleyball": {
    "height": 38,
    "pixelRatio": 2,
    "width": 38,
    "x": 38,
    "y": 456
  },
  "warehouse": {
    "height": 38,
    "pixelRatio": 2,
    "width": 38,
    "x": 76,
    "y": 456
  },
  "waste-basket": {
    "height": 38,
    "pixelRatio": 2,
    "width": 38,
    "x": 114,
    "y": 456
  },
  "watch": {
    "height": 38,
    "pixelRatio": 2,
    "width": 38,
    "x": 152,
    "y": 456
  },
  "water": {
    "height": 38,
    "pixelRatio": 2,
    "width": 38,
    "x": 190,
    "y": 456
  },
  "waterfall": {
    "height": 38,
    "pixelRatio": 2,
    "width": 38,
    "x": 228,
    "y": 456
  },
  "watermill": {
    "height": 38,
    "pixelRatio": 2,
    "width": 38,
    "x": 266,
    "y": 456
  },
  "wetland": {
    "height": 38,
    "pixelRatio": 2,
    "width": 38,
    "x": 304,
    "y": 456
  },
  "wheelchair": {
    "height": 38,
    "pixelRatio": 2,
    "width": 38,
    "x": 342,
    "y": 456
  },
  "windmill": {
    "height": 38,
    "pixelRatio": 2,
    "width": 38,
    "x": 380,
    "y": 456
  },
  "zoo": {
    "height": 38,
    "pixelRatio": 2,
    "width": 38,
    "x": 418,
    "y": 456
  }
}